README.rst
setup.py
stocktracker/__init__.py
stocktracker/dollars.py
stocktracker/importer.py
stocktracker/transactions.py
stocktracker/utility.py
stocktracker.egg-info/PKG-INFO
stocktracker.egg-info/SOURCES.txt
stocktracker.egg-info/dependency_links.txt
stocktracker.egg-info/requires.txt
stocktracker.egg-info/top_level.txt