Metadata-Version: 1.0
Name: stocktracker
Version: 0.0.2
Summary: stocktracker
Home-page: https://github.com/mgiuffrida/stocktracker
Author: Michael Giuffrida
Author-email: michaelg@michaelg.us
License: MIT
Platform: UNKNOWN
